[1,["a4vsOeVaBMfItBLla+wtKH"],["_textureSetter"],["cc.SpriteFrame"],0,[[[{"name":"chongzhi_btn","rect":[1184,621,182,69],"offset":[0,0],"originalSize":[182,69],"capInsets":[0,0,0,0]}],[0],0,[0],[0],[0]],[[{"name":"quxiao_btn","rect":[1042,580,182,69],"offset":[0,0],"originalSize":[182,69],"rotated":1,"capInsets":[0,0,0,0]}],[0],0,[0],[0],[0]],[[{"name":"queding_btn","rect":[1113,580,182,69],"offset":[0,0],"originalSize":[182,69],"rotated":1,"capInsets":[0,0,0,0]}],[0],0,[0],[0],[0]],[[{"name":"title_xiaoxi","rect":[449,659,114,61],"offset":[0,0],"originalSize":[114,61],"capInsets":[0,0,0,0]}],[0],0,[0],[0],[0]]]]