[1,["09GPXDv21CaodoAPq1C9O7"],["_textureSetter"],["cc.SpriteFrame"],0,[[[{"name":"xmlxyx_6","rect":[1,518,817,581],"offset":[0,0],"originalSize":[817,581],"capInsets":[0,0,0,0]}],[0],0,[0],[0],[0]],[[{"name":"xmlxyx_4","rect":[1,1102,817,566],"offset":[0,0],"originalSize":[817,566],"capInsets":[0,0,0,0]}],[0],0,[0],[0],[0]],[[{"name":"xmlxyx_5","rect":[821,656,196,71],"offset":[0,0],"originalSize":[196,71],"rotated":1,"capInsets":[0,0,0,0]}],[0],0,[0],[0],[0]],[[{"name":"xmlxyx_9","rect":[821,518,135,88],"offset":[0,0],"originalSize":[135,88],"rotated":1,"capInsets":[0,0,0,0]}],[0],0,[0],[0],[0]]]]