[1,["83V3Vu3fhIpJGnhi3iCy3z","539h1OhHFOAaZAaM6YaNmE","274D6ix5NIjputjxn0nhT3","8bL4Z4xWlBhZWsec1UcGhz","e406HChzxC4753j3HBIipY","18SD1wHD9Kya2n+8JOxuYO","7f946aeL5G7aYKDn79iHD9","26Voxm68ZEzK82bGp/vXYp","acNEf2Y9dNs65eo4ck6aWZ","44h4/iSVBLdbJ32ysvJQBU","85u7qOzBRBBrE2guV7Kjnl","6apRjf7PNKq5jaX5rkSuYp","68WcK/osNCJayA5ExQ7fmo","5agDZp8BtFjqcMnxWJsnFI","fea52qcx5MuIV3oI7cX2Ky","d4JbYoWW5Px7z2ymW+8cAi","b0y/jPZ75PMZkstbkCgYfq","5eQqZsx5VKQ4C3K7Ol0CtW","e1WLNThm9Gd7ycF15nVRE/","d2pIEkqVxAeLMd3tJyaS82","13dDb0QD5CK53rqOES2Tpu","32k7dEKvRJtaNjFiUM6vl3","94aBfrg5tPsK7W1AojT+RW","92y6kInPtMUKoLWXcvyGlb","ccEznsbRRO6bkH6Z8Tf9zi","a1fMlzC8ZDVIZTkGkA8e3G","19j5v0TsRIzbULGzn7EVL3","54nvKZ5MdGRpszJyzTH9QN","b5Pey7G/1FjbUcjn8o74GD","09XAyBdy9Cb6cGtcEWytZE","efIml5JN5LaKYq1ezw45nq","99VZFttWRCnLHpPpLy4XX1","07W5HGg7tBjoNwvPojUi4b","09uGfnDc9NA57Q4QjRqkSn","65J6OXvp9LNqrX6Dfzd1mv","a484SN4fBHv49EU+EwCm2T","9cayj1MaVH0pYBsB3ZnYZn","6cBBoe7XVDa4mLHvnUmORV","03PdFBdLtGXKMcWmi0QBQl","b7wMud4IRJqpy4N4PzQtct","0fn+MA1eFBN4Vy0X4L1dlP","f8GA4PIkNFJbOsN9jHx9GY","9e10rpkWVOxJfsLK8RQ4pC","2eDki9X+NGzpFQTQEuExZ3","3cRqrzJplMa4JhUXO8+Z8y","e2eLKQWBxGMqG3pcw8Nfur","c5JChko89C8bfL1yTVoq1b","d6YwJ6rVBH15qJBtOZoeuF","250udVJJNH/YBvVMHx/B8v","c2r0Kzl85K9LK7IQmKzNQ0","38JWNi/4ZEer6DXltEXXyi","1dBmEhRPFJLbc4jxaTmXVC","edT/Q2ePVGZKYQLqMr4al8","96+0dX7kFFf6KQLGSyxCO7","07ozN+7W5NtL8wFyrlDXum","d5h8CgFDJKbLFTysEO+LHV","12zjoB5XpGqrMEssVuvPlN","926mOidOtEXIf8SJGAdXhF","943j9X7ldBSp3mlDIIdng3","f5EXJSXz5LCL/0dX5lCClg","14a8pROLFItpvgKsL5AAZT","626fehMyFOh4/IcChxbeQw","e5gt6fJ7RJBqPG7hfunjA5","6boc83ToNOEI+u5puX55uX","ecDmEOc5hFlp/6e9G1R5wI","b5HW2BiwVJt763Mf2Nqtmn","6fiVIPqmFLioQcuhxYwwlw","31vzXLpmZMc41WUVyTq2di","435rOsZBpIoYvAdn8kpyBa","55u0eeo0VJf4TyYARyhmBM","d0mXD3WUJFiZzHLRuhKcz2","5aXn8cXvxI6608B+9szbpT","d03Mg5ig1LHZW5qPIo3+bS","e5ceDShsBIE5SMhhmZHRHK","237+6/vLpMo6vwLUX01tcz","55wdlktdxIsIZmkJe2IERk","b1b8XeimhIfYv5vr/sokVg","95N1EM0jVOBqrON6mZQ+rP","a2JEIsyzpLNo3N98j7tUf+","5djlmvzh5IyaaWJvydM76v","e5tPs2Pn9KOrfsOA1Ku4lM","f3Uu7BeDFPpq0hj3fjB2FE","08Vzjv/exNarFkJS74Zlhc","7eKHm+qe9CvavHH6bjyugg","a3P+aC17FPTqnrp+/CA7x5","7fk7YHKytMurYvnkSzZQsJ","f3ECNaVitBZ7toXsrNrgjp","6bDsvfmDRDG6A/uK2GEFRO","61iKpBPutJM5mQIZ3JTV3O","22srtbDFtEL6qMKnV4VjdH"],["value"],[["cc.AnimationClip",["_name","_duration","sample","wrapMode","curveData"],-1,11]],[[0,0,1,2,3,4,5]],[[0,"sglhj_xc_chujichang",1.9666666666666666,30,2,[{},"paths",11,[{},"sglhj_jackpot_mb_00",11,[{},"comps",11,[{},"cc.Sprite",11,[{},"spriteFrame",12,[[[{"frame":0},"value",6,0],[{"frame":0.06666666666666667},"value",6,1],[{"frame":0.13333333333333333},"value",6,2],[{"frame":0.2},"value",6,3],[{"frame":0.26666666666666666},"value",6,4],[{"frame":0.3333333333333333},"value",6,5],[{"frame":0.4},"value",6,6],[{"frame":0.4666666666666667},"value",6,7],[{"frame":0.5333333333333333},"value",6,8],[{"frame":0.6},"value",6,9],[{"frame":0.6666666666666666},"value",6,10],[{"frame":0.7333333333333333},"value",6,11],[{"frame":0.8},"value",6,12],[{"frame":0.8666666666666667},"value",6,13],[{"frame":0.9333333333333333},"value",6,14],[{"frame":1},"value",6,15],[{"frame":1.0666666666666667},"value",6,16],[{"frame":1.1333333333333333},"value",6,17],[{"frame":1.2},"value",6,18],[{"frame":1.2666666666666666},"value",6,19],[{"frame":1.3333333333333333},"value",6,20],[{"frame":1.4},"value",6,21],[{"frame":1.4666666666666666},"value",6,22],[{"frame":1.5333333333333334},"value",6,23],[{"frame":1.6},"value",6,24],[{"frame":1.6666666666666667},"value",6,25],[{"frame":1.7333333333333334},"value",6,26],[{"frame":1.8},"value",6,27],[{"frame":1.8666666666666667},"value",6,28],[{"frame":1.9333333333333333},"value",6,29]],11,11,11,11,11,11,11,11,11,11,11,11,11,11,11,11,11,11,11,11,11,11,11,11,11,11,11,11,11,11]]]],"sglhj_kuang_01_mb_00",11,[{},"comps",11,[{},"cc.Sprite",11,[{},"spriteFrame",12,[[[{"frame":0},"value",6,30],[{"frame":0.06666666666666667},"value",6,31],[{"frame":0.13333333333333333},"value",6,32],[{"frame":0.2},"value",6,33],[{"frame":0.26666666666666666},"value",6,34],[{"frame":0.3333333333333333},"value",6,35],[{"frame":0.4},"value",6,36],[{"frame":0.4666666666666667},"value",6,37],[{"frame":0.5333333333333333},"value",6,38],[{"frame":0.6},"value",6,39],[{"frame":0.6666666666666666},"value",6,40],[{"frame":0.7333333333333333},"value",6,41],[{"frame":0.8},"value",6,42],[{"frame":0.8666666666666667},"value",6,43],[{"frame":0.9333333333333333},"value",6,44],[{"frame":1},"value",6,45],[{"frame":1.0666666666666667},"value",6,46],[{"frame":1.1333333333333333},"value",6,47],[{"frame":1.2},"value",6,48],[{"frame":1.2666666666666666},"value",6,49],[{"frame":1.3333333333333333},"value",6,50],[{"frame":1.4},"value",6,51],[{"frame":1.4666666666666666},"value",6,52],[{"frame":1.5333333333333334},"value",6,53],[{"frame":1.6},"value",6,54],[{"frame":1.6666666666666667},"value",6,55],[{"frame":1.7333333333333334},"value",6,56],[{"frame":1.8},"value",6,57],[{"frame":1.8666666666666667},"value",6,58],[{"frame":1.9333333333333333},"value",6,59]],11,11,11,11,11,11,11,11,11,11,11,11,11,11,11,11,11,11,11,11,11,11,11,11,11,11,11,11,11,11]]]],"xmlcjc_6",11,[{},"props",11,[{"opacity":[{"frame":0.16666666666666666,"value":0},{"frame":0.8333333333333334,"value":255},{"frame":1.6666666666666667,"value":0}]},"scale",12,[[[{"frame":0.16666666666666666},"value",8,[0,1,1]],[{"frame":1.6666666666666667},"value",8,[0,1.3,1.3]]],11,11]]],"xmlcjc_bt_00",11,[{},"comps",11,[{},"cc.Sprite",11,[{},"spriteFrame",12,[[[{"frame":0},"value",6,60],[{"frame":0.06666666666666667},"value",6,61],[{"frame":0.13333333333333333},"value",6,62],[{"frame":0.2},"value",6,63],[{"frame":0.26666666666666666},"value",6,64],[{"frame":0.3333333333333333},"value",6,65],[{"frame":0.4},"value",6,66],[{"frame":0.4666666666666667},"value",6,67],[{"frame":0.5333333333333333},"value",6,68],[{"frame":0.6},"value",6,69],[{"frame":0.6666666666666666},"value",6,70],[{"frame":0.7333333333333333},"value",6,71],[{"frame":0.8},"value",6,72],[{"frame":0.8666666666666667},"value",6,73],[{"frame":0.9333333333333333},"value",6,74],[{"frame":1},"value",6,75],[{"frame":1.0666666666666667},"value",6,76],[{"frame":1.1333333333333333},"value",6,77],[{"frame":1.2},"value",6,78],[{"frame":1.2666666666666666},"value",6,79],[{"frame":1.3333333333333333},"value",6,80],[{"frame":1.4},"value",6,81],[{"frame":1.4666666666666666},"value",6,82],[{"frame":1.5333333333333334},"value",6,83],[{"frame":1.6},"value",6,84],[{"frame":1.6666666666666667},"value",6,85],[{"frame":1.7333333333333334},"value",6,86],[{"frame":1.8},"value",6,87],[{"frame":1.8666666666666667},"value",6,88],[{"frame":1.9333333333333333},"value",6,89]],11,11,11,11,11,11,11,11,11,11,11,11,11,11,11,11,11,11,11,11,11,11,11,11,11,11,11,11,11,11]]]]]]]],0,0,[0,0,0,0,0,0,0,0,0,0,0,0,0,0,0,0,0,0,0,0,0,0,0,0,0,0,0,0,0,0,0,0,0,0,0,0,0,0,0,0,0,0,0,0,0,0,0,0,0,0,0,0,0,0,0,0,0,0,0,0,0,0,0,0,0,0,0,0,0,0,0,0,0,0,0,0,0,0,0,0,0,0,0,0,0,0,0,0,0,0],[0,0,0,0,0,0,0,0,0,0,0,0,0,0,0,0,0,0,0,0,0,0,0,0,0,0,0,0,0,0,0,0,0,0,0,0,0,0,0,0,0,0,0,0,0,0,0,0,0,0,0,0,0,0,0,0,0,0,0,0,0,0,0,0,0,0,0,0,0,0,0,0,0,0,0,0,0,0,0,0,0,0,0,0,0,0,0,0,0,0],[0,1,2,3,4,5,6,7,8,9,10,11,12,13,14,15,16,17,18,19,20,21,22,23,24,25,26,27,28,29,30,31,32,33,34,35,36,37,38,39,40,41,42,43,44,45,46,47,48,49,50,51,52,53,54,55,56,57,58,59,60,61,62,63,64,65,66,67,68,69,70,71,72,73,74,75,76,77,78,79,80,81,82,83,84,85,86,87,88,89]]