[1,["72uJD8JqtFcJ3W98zY5psz"],["_textureSetter"],["cc.SpriteFrame"],0,[[[{"name":"x5","rect":[340,1971,63,45],"offset":[0,0],"originalSize":[63,45],"capInsets":[0,0,0,0]}],[0],0,[0],[0],[0]],[[{"name":"x3","rect":[305,1404,63,45],"offset":[0,0],"originalSize":[63,45],"rotated":1,"capInsets":[0,0,0,0]}],[0],0,[0],[0],[0]],[[{"name":"xz1","rect":[104,933,256,104],"offset":[0,0],"originalSize":[256,104],"capInsets":[0,0,0,0]}],[0],0,[0],[0],[0]],[[{"name":"zdxz2","rect":[229,1919,97,109],"offset":[0,0],"originalSize":[97,109],"rotated":1,"capInsets":[0,0,0,0]}],[0],0,[0],[0],[0]],[[{"name":"x10","rect":[259,1872,87,45],"offset":[0,0],"originalSize":[87,45],"capInsets":[0,0,0,0]}],[0],0,[0],[0],[0]],[[{"name":"jia2","rect":[166,1580,70,109],"offset":[0,0],"originalSize":[70,109],"rotated":1,"capInsets":[0,0,0,0]}],[0],0,[0],[0],[0]],[[{"name":"jian1","rect":[277,1540,70,109],"offset":[0,0],"originalSize":[70,109],"capInsets":[0,0,0,0]}],[0],0,[0],[0],[0]],[[{"name":"x2","rect":[277,1651,63,45],"offset":[0,0],"originalSize":[63,45],"capInsets":[0,0,0,0]}],[0],0,[0],[0],[0]],[[{"name":"x4","rect":[340,1825,64,45],"offset":[0,0],"originalSize":[64,45],"capInsets":[0,0,0,0]}],[0],0,[0],[0],[0]],[[{"name":"jian2","rect":[166,1508,70,109],"offset":[0,0],"originalSize":[70,109],"rotated":1,"capInsets":[0,0,0,0]}],[0],0,[0],[0],[0]],[[{"name":"zdxz1","rect":[166,1409,97,109],"offset":[0,0],"originalSize":[97,109],"rotated":1,"capInsets":[0,0,0,0]}],[0],0,[0],[0],[0]],[[{"name":"zyz","rect":[104,1773,149,100],"offset":[0,0],"originalSize":[149,100],"rotated":1,"capInsets":[0,0,0,0]}],[0],0,[0],[0],[0]],[[{"name":"stop1","rect":[104,1145,256,104],"offset":[0,0],"originalSize":[256,104],"capInsets":[0,0,0,0]}],[0],0,[0],[0],[0]],[[{"name":"zjje","rect":[2,30,364,114],"offset":[0,0],"originalSize":[364,114],"capInsets":[0,0,0,0]}],[0],0,[0],[0],[0]],[[{"name":"freespin","rect":[104,1251,256,104],"offset":[0,0],"originalSize":[256,104],"capInsets":[0,0,0,0]}],[0],0,[0],[0],[0]],[[{"name":"jia1","rect":[166,1652,70,109],"offset":[0,0],"originalSize":[70,109],"capInsets":[0,0,0,0]}],[0],0,[0],[0],[0]]]]