{
    // 游戏配置
    "game_config" : {

        // 满桌时间概率分布
        "full_table_time_rate": [10, 20, 30, 40, 50, 60, 70, 80, 90, 100],

        // 控制配置信息
        "control": {

            // 作弊率等级
            "control_rate": [3000, 2000, 1000, -1000, -2000, -3000],

            // 玩家最大牌概率分布
            "player_biggest_rate": [0, 0, 1000, 1500, 2000, 2500],

            // 机器人最大牌概率分布
            "robot_biggest_rate": [3000, 2200, 1800, 1400, 1000, 600],

            // 玩家换牌概率分布
            "exchange_rate": [10000, 5000, 4333, 0, 0, 0],

            // 机器人造炸弹概率分布
            "build_boom_rate": [10000, 5000, 3500, 0, 0, 0],

            // 换大小三同张或者对子概率分布
            "exchange_block_rate": [10000, 5000, 3500, 0, 0, 0]
        }
    },

    // 时间配置
    "time_config" : {

        // 执行时间
        "operation_time": 15000,

        // 过渡时间
        "excessive_time": 2000,

        // 过渡时间
        "space_time": 6000,

        // 轮询检测添加机器人时间
        "robot_sit_check": 500,

        // 轮询检测添加机器人时间
        "one_second": 1500
    }
}