[1,["59obGypVFBTa/xZhHMMHA/"],["_textureSetter"],["cc.SpriteFrame"],0,[[[{"name":"effects_wlzb_zj_freegame_11_00006","rect":[1,610,200,200],"offset":[0,0],"originalSize":[200,200],"capInsets":[0,0,0,0]}],[0],0,[0],[0],[0]],[[{"name":"effects_wlzb_zj_freegame_11_00007","rect":[1,1016,200,198],"offset":[0,1],"originalSize":[200,200],"capInsets":[0,0,0,0]}],[0],0,[0],[0],[0]],[[{"name":"effects_wlzb_zj_freegame_11_00008","rect":[204,1016,200,198],"offset":[0,1],"originalSize":[200,200],"capInsets":[0,0,0,0]}],[0],0,[0],[0],[0]],[[{"name":"effects_wlzb_zj_freegame_11_00001","rect":[204,1,200,200],"offset":[0,0],"originalSize":[200,200],"capInsets":[0,0,0,0]}],[0],0,[0],[0],[0]],[[{"name":"effects_wlzb_zj_freegame_11_00004","rect":[1,407,200,200],"offset":[0,0],"originalSize":[200,200],"capInsets":[0,0,0,0]}],[0],0,[0],[0],[0]],[[{"name":"effects_wlzb_zj_freegame_11_00003","rect":[204,204,200,200],"offset":[0,0],"originalSize":[200,200],"capInsets":[0,0,0,0]}],[0],0,[0],[0],[0]],[[{"name":"effects_wlzb_zj_freegame_11_00010","rect":[1,813,200,200],"offset":[0,0],"originalSize":[200,200],"capInsets":[0,0,0,0]}],[0],0,[0],[0],[0]],[[{"name":"effects_wlzb_zj_freegame_11_00009","rect":[204,610,200,200],"offset":[0,0],"originalSize":[200,200],"capInsets":[0,0,0,0]}],[0],0,[0],[0],[0]],[[{"name":"effects_wlzb_zj_freegame_11_00002","rect":[1,204,200,200],"offset":[0,0],"originalSize":[200,200],"capInsets":[0,0,0,0]}],[0],0,[0],[0],[0]],[[{"name":"effects_wlzb_zj_freegame_11_00005","rect":[204,407,200,200],"offset":[0,0],"originalSize":[200,200],"capInsets":[0,0,0,0]}],[0],0,[0],[0],[0]],[[{"name":"effects_wlzb_zj_freegame_11_00000","rect":[1,1,200,200],"offset":[0,0],"originalSize":[200,200],"capInsets":[0,0,0,0]}],[0],0,[0],[0],[0]],[[{"name":"effects_wlzb_zj_freegame_11_00011","rect":[204,813,200,200],"offset":[0,0],"originalSize":[200,200],"capInsets":[0,0,0,0]}],[0],0,[0],[0],[0]]]]