[1,["d6Xm5tN9JL3oVEV0IvVPHz"],["_textureSetter"],["cc.SpriteFrame"],0,[[[{"name":"zongtouzhu","rect":[645,949,82,31],"offset":[0,0],"originalSize":[82,31],"capInsets":[0,0,0,0]}],[0],0,[0],[0],[0]],[[{"name":"zongyingqu","rect":[188,979,88,32],"offset":[0,0],"originalSize":[88,32],"capInsets":[0,0,0,0]}],[0],0,[0],[0],[0]],[[{"name":"deng4","rect":[835,2,23,420],"offset":[0,1],"originalSize":[23,422],"capInsets":[0,0,0,0]}],[0],0,[0],[0],[0]],[[{"name":"jia_btn_disable","rect":[931,135,68,52],"offset":[0,0],"originalSize":[68,52],"capInsets":[0,0,0,0]}],[0],0,[0],[0],[0]],[[{"name":"zongtouzhu_bg","rect":[885,236,162,40],"offset":[0,0],"originalSize":[162,40],"rotated":1,"capInsets":[0,0,0,0]}],[0],0,[0],[0],[0]],[[{"name":"shuiguo777","rect":[2,877,332,100],"offset":[0,0],"originalSize":[332,100],"capInsets":[0,0,0,0]}],[0],0,[0],[0],[0]],[[{"name":"zidong_btn","rect":[860,422,152,97],"offset":[0,0],"originalSize":[152,97],"capInsets":[0,0,0,0]}],[0],0,[0],[0],[0]],[[{"name":"jian_btn_down","rect":[435,949,68,52],"offset":[0,0],"originalSize":[68,52],"capInsets":[0,0,0,0]}],[0],0,[0],[0],[0]],[[{"name":"jian_btn","rect":[929,915,68,52],"offset":[0,0],"originalSize":[68,52],"capInsets":[0,0,0,0]}],[0],0,[0],[0],[0]],[[{"name":"tingzhi_btn","rect":[860,620,152,97],"offset":[0,0],"originalSize":[152,97],"capInsets":[0,0,0,0]}],[0],0,[0],[0],[0]],[[{"name":"jia_btn","rect":[575,949,68,52],"offset":[0,0],"originalSize":[68,52],"capInsets":[0,0,0,0]}],[0],0,[0],[0],[0]],[[{"name":"jian_btn_disable","rect":[931,81,68,52],"offset":[0,0],"originalSize":[68,52],"capInsets":[0,0,0,0]}],[0],0,[0],[0],[0]],[[{"name":"xuanzhuan_btn","rect":[860,521,152,97],"offset":[0,0],"originalSize":[152,97],"capInsets":[0,0,0,0]}],[0],0,[0],[0],[0]],[[{"name":"zuidatouzhu_btn","rect":[336,877,132,97],"offset":[0,0],"originalSize":[132,97],"rotated":1,"capInsets":[0,0,0,0]}],[0],0,[0],[0],[0]],[[{"name":"xuanzhuan_btn_down","rect":[435,852,152,95],"offset":[0,-1],"originalSize":[152,97],"capInsets":[0,0,0,0]}],[0],0,[0],[0],[0]],[[{"name":"zhegai","rect":[2,427,831,423],"offset":[0,0],"originalSize":[831,423],"capInsets":[0,0,0,0]}],[0],0,[0],[0],[0]],[[{"name":"9xian","rect":[931,189,58,37],"offset":[3,0],"originalSize":[72,37],"capInsets":[0,0,0,0]}],[0],0,[0],[0],[0]],[[{"name":"jia_btn_down","rect":[505,949,68,52],"offset":[0,0],"originalSize":[68,52],"capInsets":[0,0,0,0]}],[0],0,[0],[0],[0]],[[{"name":"zhegai1","rect":[2,2,831,423],"offset":[0,0],"originalSize":[831,423],"capInsets":[0,0,0,0]}],[0],0,[0],[0],[0]],[[{"name":"deng3","rect":[2,852,23,420],"offset":[0,1],"originalSize":[23,422],"rotated":1,"capInsets":[0,0,0,0]}],[0],0,[0],[0],[0]],[[{"name":"zongyingqu_bg","rect":[885,2,232,44],"offset":[0,0],"originalSize":[232,44],"rotated":1,"capInsets":[0,0,0,0]}],[0],0,[0],[0],[0]],[[{"name":"deng2","rect":[835,424,23,418],"offset":[0,0],"originalSize":[23,418],"capInsets":[0,0,0,0]}],[0],0,[0],[0],[0]],[[{"name":"touxiangkuang","rect":[931,2,76,77],"offset":[0,0],"originalSize":[76,77],"capInsets":[0,0,0,0]}],[0],0,[0],[0],[0]],[[{"name":"jinbi_bg","rect":[2,979,184,36],"offset":[0,0],"originalSize":[184,36],"capInsets":[0,0,0,0]}],[0],0,[0],[0],[0]],[[{"name":"tingzhi_btn_down","rect":[589,852,152,95],"offset":[0,-1],"originalSize":[152,97],"capInsets":[0,0,0,0]}],[0],0,[0],[0],[0]],[[{"name":"deng1","rect":[860,2,23,418],"offset":[0,0],"originalSize":[23,418],"capInsets":[0,0,0,0]}],[0],0,[0],[0],[0]],[[{"name":"zidong_btn_down","rect":[860,818,152,95],"offset":[0,-1],"originalSize":[152,97],"capInsets":[0,0,0,0]}],[0],0,[0],[0],[0]],[[{"name":"zuidatouzhu_btn_down","rect":[743,852,132,95],"offset":[0,-1],"originalSize":[132,97],"rotated":1,"capInsets":[0,0,0,0]}],[0],0,[0],[0],[0]],[[{"name":"mianfei_btn","rect":[860,719,152,97],"offset":[0,0],"originalSize":[152,97],"capInsets":[0,0,0,0]}],[0],0,[0],[0],[0]]]]