[1,["d16ZXedAhHq7akMoKXwWs9","9bvaMerUlDyary99mJa6xp","91DFXSzBFF9KZv8Q/S9X3m","e3IMDyzKtMb4OHvngXBSca","79NNqgtt9NW47UGytlNIRl","d09otmCSRFM6k+9p7EjrB2","e97GVMl6JHh5Ml5qEDdSGa","f0BIwQ8D5Ml7nTNQbh1YlS","29FYIk+N1GYaeWH/q1NxQO","ddOzK7GyxI0KVRpZRGYVQl","0aWGDYtMhHj6pbwW0OoCdr","efZxBBHUFNiatZoBWwtH/Q"],["node","_spriteFrame","_textureSetter","_parent","root","target","data","_N$pressedSprite","_N$hoverSprite","_N$disabledSprite"],[["cc.Node",["_name","_opacity","_components","_prefab","_contentSize","_children","_parent","_trs","_anchorPoint","_color"],1,9,4,5,2,1,7,5,5],"cc.SpriteFrame",["cc.Button",["_N$transition","node","clickEvents","_N$normalColor","_N$pressedColor","_N$disabledColor","_N$target","_N$pressedSprite","_N$hoverSprite","_N$disabledSprite"],2,1,9,5,5,5,1,6,6,6],["cc.Layout",["_resize","_N$layoutType","_N$spacingY","node","_layoutSize"],0,1,5],["cc.Sprite",["_type","_sizeMode","node","_spriteFrame"],1,1,6],["cc.Prefab",["_name"],2],["6ac72To78VEa6pFOYqIfVr/",["node"],3,1],["cc.ClickEvent",["_componentId","handler","target"],1,1],["cc.PrefabInfo",["fileId","root"],2,1],["cc.BlockInputEvents",["node"],3,1],["cc.Widget",["alignMode","_alignFlags","_originalWidth","_originalHeight","node"],-1,1],["cc.PageView",["bounceDuration","node","_N$content"],2,1,1],["cc.Mask",["_N$alphaThreshold","node"],2,1]],[[8,0,1,2],[4,0,1,2,3,3],[0,0,6,5,2,3,4,7,2],[0,0,6,2,3,4,7,2],[4,2,3,1],[0,0,6,5,2,3,4,2],[7,0,1,2,3],[5,0,2],[0,0,5,2,3,4,2],[0,0,5,2,3,4,8,7,2],[0,0,2,3,4,2],[0,0,1,6,2,3,9,4,3],[6,0,1],[2,1,2,3,1],[2,0,1,2,3,4,5,6,7,8,9,2],[3,0,1,2,3,4,4],[3,3,4,1],[9,0,1],[10,0,1,2,3,4,5],[11,0,1,2,2],[12,0,1,2]],[[[{"name":"yiye","rect":[1,4,642,273],"offset":[0.5,4.5],"originalSize":[643,290],"capInsets":[0,0,0,0]}],[1],0,[0],[2],[0]],[[[7,"helpLayer"],[8,"helpLayer",[-5,-6,-7,-8],[[12,-2],[13,-4,[[6,"6ac72To78VEa6pFOYqIfVr/","closeLayer",-3]],[4,4292269782]]],[0,"f4W55mgktAAr4FRM5CrfMx",-1],[5,1624,750]],[9,"content",[-10,-11],[[15,1,1,15,-9,[5,1100,300]]],[0,"dcI6vUUClNdYpbyXI/IIZA",1],[5,1100,300],[0,0,0.5],[-275,0,0,0,0,0,1,1,1,1]],[5,"back",1,[-14],[[4,-12,3],[17,-13]],[0,"63qxyh735A+4cguKMSH286",1],[5,639,416]],[10,"Background",[[1,1,0,-15,4],[18,0,45,100,40,-16]],[0,"bbIvYzeB5MapkWyiThLzFd",1],[5,56,57]],[11,"Layout",204,1,[[1,1,0,-17,0],[16,-18,[5,1624,750]]],[0,"3aXgqlxLtJeoxelupJHcYJ",1],[4,4278190080],[5,1624,750]],[2,"biaotilan",3,[-20],[[4,-19,2]],[0,"f9s0L4b31JRKyUuMxh2feN",1],[5,237,60],[0,171.12,0,0,0,0,1,1,1,1]],[2,"close",1,[4],[[14,3,-21,[[6,"6ac72To78VEa6pFOYqIfVr/","closeLayer",1]],[4,4293322470],[4,4291348680],[4,3363338360],4,5,6,7]],[0,"4ae9D24ydJNrP6oTtsOPAv",1],[5,56,57],[283,176,0,0,0,0,1,1,1,1]],[2,"PageView",1,[-23],[[19,0.5,-22,2]],[0,"44y5JDTy5CoqXWbGv2+FWr",1],[5,550,300],[0,-20,0,0,0,0,1,1,1,1]],[5,"view",8,[2],[[20,0,-24]],[0,"14jzUYxRlAx6E6PJUVLpqb",1],[5,550,300]],[3,"guize",6,[[4,-25,1]],[0,"1eXwa3ldNPeJ+wPjqPaUPj",1],[5,75,33],[0,3,0,0,0,0,1,1,1,1]],[3,"page_1",2,[[1,1,0,-26,8]],[0,"ebGmHlOvJGNpiib8RjXAqB",1],[5,550,290],[275,0,0,0,0,0,1,1,1,1]],[3,"page_2",2,[[1,1,0,-27,9]],[0,"7adb6w1u9LUobxRbdaD4Lj",1],[5,550,290],[825,0,0,0,0,0,1,1,1,1]]],0,[0,4,1,0,0,1,0,5,1,0,0,1,0,-1,5,0,-2,3,0,-3,7,0,-4,8,0,0,2,0,-1,11,0,-2,12,0,0,3,0,0,3,0,-1,6,0,0,4,0,0,4,0,0,5,0,0,5,0,0,6,0,-1,10,0,0,7,0,0,8,0,-1,9,0,0,9,0,0,10,0,0,11,0,0,12,0,6,1,2,3,9,4,3,7,27],[0,0,0,0,0,0,0,0,0,0],[1,1,1,1,1,7,8,9,1,1],[1,2,3,4,5,6,7,8,9,10]],[[{"name":"erye","rect":[1,0,642,290],"offset":[0.5,0],"originalSize":[643,290],"capInsets":[0,0,0,0]}],[1],0,[0],[2],[11]]]]