[1,["3163D32wBBSJhjsi1H4pcw"],["_textureSetter"],["cc.SpriteFrame"],0,[[[{"name":"quxiao_btn","rect":[1576,1076,264,80],"offset":[0,0],"originalSize":[264,80],"rotated":1,"capInsets":[0,0,0,0]}],[0],0,[0],[0],[0]],[[{"name":"qwcz_btn","rect":[1576,810,264,80],"offset":[0,0],"originalSize":[264,80],"rotated":1,"capInsets":[0,0,0,0]}],[0],0,[0],[0],[0]],[[{"name":"queding_btn","rect":[1576,1342,264,80],"offset":[0,0],"originalSize":[264,80],"rotated":1,"capInsets":[0,0,0,0]}],[0],0,[0],[0],[0]],[[{"name":"tishi_bg","rect":[1240,2,806,464],"offset":[0,0],"originalSize":[806,464],"rotated":1,"capInsets":[0,0,0,0]}],[0],0,[0],[0],[0]]]]